Workbook

Sheet Cover
B2: PROJECT ATLAS - 50 MWp Solar PV, France
B3: Ground-mounted solar - Nouvelle-Aquitaine - Project finance model - Base case with sensititvity analysis
B6: PROJECT SUMMARY
B7: • 50 MWp ground-mounted solar PV - Nouvelle-Aquitaine, France
B8: • 20-year CRE (CfD) contract at €79/MWh, then 5-year merchant tail at €55/MWh (real)
B9: • €41.0m capex · €43.6m total funded cost · 75% senior debt on capex, financing costs equity-funded
B10: • 18-year senior facility · sculpted to 1.55x contracted DSCR · 4.75% all-in fixed rate
B12: HEADLINE OUTPUTS
B13: Project IRR (unlevered) | C13: =Returns!C34 -> 0.072321667 | E13: Minimum DSCR | F13: =Debt!C39 -> 1.3723361
B14: Equity IRR (levered) | C14: =Returns!C41 -> 0.10736353 | E14: Average DSCR | F14: =Debt!C40 -> 1.6189127
B15: Equity multiple (MOIC) | C15: =Returns!C43 -> 3.36665 | E15: Minimum LLCR | F15: =Returns!C27 -> 1.6087553
B16: Equity payback | C16: =Returns!C45 -> Year 11 | E16: Senior debt | F16: =Debt!C22 -> 30.75
B17: Gearing (on capex) | C17: =Inputs!C18 -> 0.75 | E17: Equity | F17: =Construction!C42 -> 12.894555
E18: Binding constraint | F18: =Debt!C23 -> Gearing-based
B20: MODEL INTEGRITY
B21: =Checks!C7 -> ALL CHECKS PASS
B23: STATED SIMPLIFICATIONS
B24: – Debt sized on pre-tax CFADS (= EBITDA); post-tax DSCR tested separately, clears at 1.37x
B25: – IDC circularity broken via manual Goal Seek, no iterative calculation used
B26: – Financing costs (IDC, fees, DSRA) equity-funded; gearing is 75% of capex, ~70% of total cost
B27: – DSRA included in depreciation base (immaterial); no working capital modelled
B28: – No refinancing, no construction-delay scenario, straight-line tax depreciation
B29: – Merchant tail flat at €55/MWh (real)
B31: KEY ASSUMPTIONS & SOURCES
B32: Assumption | C32: Value | E32: Source / basis
B33: Capacity | C33: 50 MWp | E33: Design
B34: Yield (P50) | C34: 1,402 kWh/kWp | E34: PVGIS site query
B35: Capex | C35: €820/kWp | E35: IRENA / Fraunhofer ISE, EU utility-scale
B36: Contract price | C36: €79/MWh (20 yr) | E36: Recent CRE PPE2 ground-mount tender avg
B37: Merchant tail | C37: €55/MWh real (5 yr) | E37: Conservative assumption
B38: All-in debt rate | C38: 4.75% fixed | E38: Mid-swap + 175bp margin (judgement)
B39: Target DSCR | C39: 1.55x / 1.60x | E39: Contracted / merchant (judgement)
B41: Self-built for skills demonstration only

Sheet Inputs
B2: INPUTS - Assumptions & sources
B4: Construction_periods | C4: 2
B5: Ops_periods | C5: 50
B6: Cfd_periods | C6: 40
B7: Debt_tenor_periods | C7: 36
B9: capacity_kwp | C9: 50000
B10: yield_y1_kwh/kwp | C10: 1402
B11: degradation/yr | C11: 0.005
B12: availibility | C12: 0.985
B13: total_capex/kwp | C13: 820
B14: annual_opex/kwp | C14: 16
B15: contracted_price/MWh | C15: 79
B16: merchant_tail_price/MWh | C16: 55
B17: asset_life_yrs | C17: 25
B18: max_debt_gearing | C18: 0.75 | D18: On CAPEX spend only
B19: target_DSCR_Contracted | C19: 1.55
B20: target_DSCR_Merchant | C20: 1.6
B21: debt_rate | C21: 0.0475
B22: DSRA_forward_debt_service_months | C22: 6
B23: corporate_tax_rate | C23: 0.25
B24: depreciation_yrs | C24: 20
B25: depreciation_periods | C25: =C24*2 -> 40
B26: total_periods_semiannual | C26: 52
B27: Indexed inflation | C27: 0.02

Sheet Timing
B2: TIMING - Period calendar & flags
B4: Period number | E4: 1 | F4: =E4+1 -> 2 | G4: =F4+1 -> 3 | H4: =G4+1 -> 4 | I4: =H4+1 -> 5 | J4: =I4+1 -> 6 | K4: =J4+1 -> 7 | L4: =K4+1 -> 8 | M4: =L4+1 -> 9 | ... BD4: =BC4+1 -> 52
B5: Period start date | D5: 46113 | E5: =EDATE(D5,6) -> 46296 | F5: =EDATE(E5,6) -> 46478 | G5: =EDATE(F5,6) -> 46661 | H5: =EDATE(G5,6) -> 46844 | I5: =EDATE(H5,6) -> 47027 | J5: =EDATE(I5,6) -> 47209 | K5: =EDATE(J5,6) -> 47392 | L5: =EDATE(K5,6) -> 47574 | ... BD5: =EDATE(BC5,6) -> 55610
B6: Period end date | E6: =EOMONTH(E5,5) -> 46477 | F6: =EOMONTH(F5,5) -> 46660 | G6: =EOMONTH(G5,5) -> 46843 | H6: =EOMONTH(H5,5) -> 47026 | I6: =EOMONTH(I5,5) -> 47208 | J6: =EOMONTH(J5,5) -> 47391 | K6: =EOMONTH(K5,5) -> 47573 | L6: =EOMONTH(L5,5) -> 47756 | ... BD6: =EOMONTH(BD5,5) -> 55792
B7: Days in period | E7: =E6-E5+1 -> 182 | F7: =F6-F5+1 -> 183 | G7: =G6-G5+1 -> 183 | H7: =H6-H5+1 -> 183 | I7: =I6-I5+1 -> 182 | J7: =J6-J5+1 -> 183 | K7: =K6-K5+1 -> 182 | L7: =L6-L5+1 -> 183 | ... BD7: =BD6-BD5+1 -> 183
B8: Year Fraction | E8: =E7/365 -> 0.49863014 | F8: =F7/365 -> 0.50136986 | G8: =G7/365 -> 0.50136986 | H8: =H7/365 -> 0.50136986 | I8: =I7/365 -> 0.49863014 | J8: =J7/365 -> 0.50136986 | K8: =K7/365 -> 0.49863014 | L8: =L7/365 -> 0.50136986 | ... BD8: =BD7/365 -> 0.50136986
B10: Construction flag | E10: =IF(E4<=Inputs!$C$4,1,0) -> 1 | F10: =IF(F4<=Inputs!$C$4,1,0) -> 1 | G10: =IF(G4<=Inputs!$C$4,1,0) -> 0 | H10: =IF(H4<=Inputs!$C$4,1,0) -> 0 | I10: =IF(I4<=Inputs!$C$4,1,0) -> 0 | J10: =IF(J4<=Inputs!$C$4,1,0) -> 0 | K10: =IF(K4<=Inputs!$C$4,1,0) -> 0 | L10: =IF(L4<=Inputs!$C$4,1,0) -> 0 | ... BD10: =IF(BD4<=Inputs!$C$4,1,0) -> 0
B11: Operations flag | E11: =IF(AND(E4>Inputs!$C$4,Timing!E4<=(Inputs!$C$5+Inputs!$C$4)),1,0) -> 0 | F11: =IF(AND(F4>Inputs!$C$4,Timing!F4<=(Inputs!$C$5+Inputs!$C$4)),1,0) -> 0 | G11: =IF(AND(G4>Inputs!$C$4,Timing!G4<=(Inputs!$C$5+Inputs!$C$4)),1,0) -> 1 | H11: =IF(AND(H4>Inputs!$C$4,Timing!H4<=(Inputs!$C$5+Inputs!$C$4)),1,0) -> 1 | I11: =IF(AND(I4>Inputs!$C$4,Timing!I4<=(Inputs!$C$5+Inputs!$C$4)),1,0) -> 1 | J11: =IF(AND(J4>Inputs!$C$4,Timing!J4<=(Inputs!$C$5+Inputs!$C$4)),1,0) -> 1 | K11: =IF(AND(K4>Inputs!$C$4,Timing!K4<=(Inputs!$C$5+Inputs!$C$4)),1,0) -> 1 | L11: =IF(AND(L4>Inputs!$C$4,Timing!L4<=(Inputs!$C$5+Inputs!$C$4)),1,0) -> 1 | ... BD11: =IF(AND(BD4>Inputs!$C$4,Timing!BD4<=(Inputs!$C$5+Inputs!$C$4)),1,0) -> 1
B12: Operating period number | E12: =IF(E11=1,E4-Inputs!$C$4,0) -> 0 | F12: =IF(F11=1,F4-Inputs!$C$4,0) -> 0 | G12: =IF(G11=1,G4-Inputs!$C$4,0) -> 1 | H12: =IF(H11=1,H4-Inputs!$C$4,0) -> 2 | I12: =IF(I11=1,I4-Inputs!$C$4,0) -> 3 | J12: =IF(J11=1,J4-Inputs!$C$4,0) -> 4 | K12: =IF(K11=1,K4-Inputs!$C$4,0) -> 5 | L12: =IF(L11=1,L4-Inputs!$C$4,0) -> 6 | ... BD12: =IF(BD11=1,BD4-Inputs!$C$4,0) -> 50
B13: Operating year number | E13: =IF(E11=1,ROUNDUP(E12/2,0),0) -> 0 | F13: =IF(F11=1,ROUNDUP(F12/2,0),0) -> 0 | G13: =IF(G11=1,ROUNDUP(G12/2,0),0) -> 1 | H13: =IF(H11=1,ROUNDUP(H12/2,0),0) -> 1 | I13: =IF(I11=1,ROUNDUP(I12/2,0),0) -> 2 | J13: =IF(J11=1,ROUNDUP(J12/2,0),0) -> 2 | K13: =IF(K11=1,ROUNDUP(K12/2,0),0) -> 3 | L13: =IF(L11=1,ROUNDUP(L12/2,0),0) -> 3 | ... BD13: =IF(BD11=1,ROUNDUP(BD12/2,0),0) -> 25
B15: Contracted flag | E15: =IF(AND(E11=1,E12<=Inputs!$C$6),1,0) -> 0 | F15: =IF(AND(F11=1,F12<=Inputs!$C$6),1,0) -> 0 | G15: =IF(AND(G11=1,G12<=Inputs!$C$6),1,0) -> 1 | H15: =IF(AND(H11=1,H12<=Inputs!$C$6),1,0) -> 1 | I15: =IF(AND(I11=1,I12<=Inputs!$C$6),1,0) -> 1 | J15: =IF(AND(J11=1,J12<=Inputs!$C$6),1,0) -> 1 | K15: =IF(AND(K11=1,K12<=Inputs!$C$6),1,0) -> 1 | L15: =IF(AND(L11=1,L12<=Inputs!$C$6),1,0) -> 1 | ... BD15: =IF(AND(BD11=1,BD12<=Inputs!$C$6),1,0) -> 0
B16: Merchant flag | E16: =IF(AND(E11=1,E15=0),1,0) -> 0 | F16: =IF(AND(F11=1,F15=0),1,0) -> 0 | G16: =IF(AND(G11=1,G15=0),1,0) -> 0 | H16: =IF(AND(H11=1,H15=0),1,0) -> 0 | I16: =IF(AND(I11=1,I15=0),1,0) -> 0 | J16: =IF(AND(J11=1,J15=0),1,0) -> 0 | K16: =IF(AND(K11=1,K15=0),1,0) -> 0 | L16: =IF(AND(L11=1,L15=0),1,0) -> 0 | ... BD16: =IF(AND(BD11=1,BD15=0),1,0) -> 1
B17: Debt repayment flag | E17: =IF(AND(E11=1,E12<=Inputs!$C$7),1,0) -> 0 | F17: =IF(AND(F11=1,F12<=Inputs!$C$7),1,0) -> 0 | G17: =IF(AND(G11=1,G12<=Inputs!$C$7),1,0) -> 1 | H17: =IF(AND(H11=1,H12<=Inputs!$C$7),1,0) -> 1 | I17: =IF(AND(I11=1,I12<=Inputs!$C$7),1,0) -> 1 | J17: =IF(AND(J11=1,J12<=Inputs!$C$7),1,0) -> 1 | K17: =IF(AND(K11=1,K12<=Inputs!$C$7),1,0) -> 1 | L17: =IF(AND(L11=1,L12<=Inputs!$C$7),1,0) -> 1 | ... BD17: =IF(AND(BD11=1,BD12<=Inputs!$C$7),1,0) -> 0
B18: Depreciation flag | E18: =IF(AND(E11=1,E12<=Inputs!$C$25),1,0) -> 0 | F18: =IF(AND(F11=1,F12<=Inputs!$C$25),1,0) -> 0 | G18: =IF(AND(G11=1,G12<=Inputs!$C$25),1,0) -> 1 | H18: =IF(AND(H11=1,H12<=Inputs!$C$25),1,0) -> 1 | I18: =IF(AND(I11=1,I12<=Inputs!$C$25),1,0) -> 1 | J18: =IF(AND(J11=1,J12<=Inputs!$C$25),1,0) -> 1 | K18: =IF(AND(K11=1,K12<=Inputs!$C$25),1,0) -> 1 | L18: =IF(AND(L11=1,L12<=Inputs!$C$25),1,0) -> 1 | ... BD18: =IF(AND(BD11=1,BD12<=Inputs!$C$25),1,0) -> 0

Sheet Construction
B2: CONSTRUCTION - Capex, funding & IDC
B5: Period number | E5: 1 | F5: =E5+1 -> 2 | G5: =F5+1 -> 3 | H5: =G5+1 -> 4 | I5: =H5+1 -> 5 | J5: =I5+1 -> 6 | K5: =J5+1 -> 7 | L5: =K5+1 -> 8 | M5: =L5+1 -> 9 | ... BD5: =BC5+1 -> 52
B7: Capex profile % | E7: 0.5 | F7: 0.5
B8: Capex spend (millions) | E8: =(E7*Inputs!$C$9*Inputs!$C$13/1000000) -> 20.5 | F8: =F7*Inputs!$C$9*Inputs!$C$13/1000000 -> 20.5
B9: Cumulative Capex (millions) | E9: =E8 -> 20.5 | F9: =E9+F8 -> 41
B11: Financing fees (1% of debt) | E11: 0.33 | F11: 0
B12: DSRA initial funding | E12: 1.57 | F12: 0
B14: Debt drawn | E14: =(E8)*Inputs!$C$18 -> 15.375 | F14: =(F8)*Inputs!$C$18 -> 15.375
B15: Equity drawn | E15: =(E8*(1-Inputs!C18))+(E11+E12+E20+F20) -> 7.7695549 | F15: =(F8+F11+F12)*(1-Inputs!$C$18) -> 5.125
B17: Debt balance b/f | E17: 0 | F17: =E24 -> 15.55926 | G17: =F24 -> 31.494555
B18: Debt drawn in period | E18: =E14 -> 15.375 | F18: =F14 -> 15.375
B20: IDC in period (Assumed) | E20: 0.18426 | F20: 0.56029491
B21: IDC in period (Calculated) | E21: =(E17+E24)/2*Inputs!C21*Timing!E8 -> 0.18426 | F21: =(F17+F24)/2*Inputs!C21*Timing!F8 -> 0.56029491
B22: IDC check | E22: =E21-E20 -> 0 | F22: =F21-F20 -> 0
B24: Debt balance c/f | E24: =E18+E20+E17 -> 15.55926 | F24: =F17+F20+F18 -> 31.494555
B27: SOURCES AND USES
B29: USES:
B31: Capex | C31: =SUM(E8:F8) -> 41
B32: IDC (Capitalised) | C32: =SUM(E20:F20) -> 0.74455492
B33: Financing fees (1% of debt) | C33: =E11 -> 0.33
B34: DSRA Initial funding | C34: =E12 -> 1.57
B36: Total uses | C36: =SUM(C31:C34) -> 43.644555
B39: SOURCES:
B41: Senior Debt | C41: =Debt!C22 -> 30.75
B42: Equity | C42: =SUM(E15:F15) -> 12.894555
B44: Total Sources | C44: =SUM(C41:C42) -> 43.644555
B46: Check (Uses-Sources) | C46: =C36-C44 -> 0

Sheet Operations
B2: OPERATIONS - Production, revenue & CFADS
B5: Period number | E5: 1 | F5: =E5+1 -> 2 | G5: =F5+1 -> 3 | H5: =G5+1 -> 4 | I5: =H5+1 -> 5 | J5: =I5+1 -> 6 | K5: =J5+1 -> 7 | L5: =K5+1 -> 8 | M5: =L5+1 -> 9 | ... BD5: =BC5+1 -> 52
B6: Operating year number | E6: =Timing!E13 -> 0 | F6: =Timing!F13 -> 0 | G6: =Timing!G13 -> 1 | H6: =Timing!H13 -> 1 | I6: =Timing!I13 -> 2 | J6: =Timing!J13 -> 2 | K6: =Timing!K13 -> 3 | L6: =Timing!L13 -> 3 | ... BD6: =Timing!BD13 -> 25
B8: ELECTRICITY PRODUCTION
B10: Degradation factor | E10: =IF(Operations!E6>0,(1-Inputs!$C$11)^(Operations!E6-1),0) -> 0 | F10: =IF(Operations!F6>0,(1-Inputs!$C$11)^(Operations!F6-1),0) -> 0 | G10: =IF(Operations!G6>0,(1-Inputs!$C$11)^(Operations!G6-1),0) -> 1 | H10: =IF(Operations!H6>0,(1-Inputs!$C$11)^(Operations!H6-1),0) -> 1 | I10: =IF(Operations!I6>0,(1-Inputs!$C$11)^(Operations!I6-1),0) -> 0.995 | J10: =IF(Operations!J6>0,(1-Inputs!$C$11)^(Operations!J6-1),0) -> 0.995 | K10: =IF(Operations!K6>0,(1-Inputs!$C$11)^(Operations!K6-1),0) -> 0.990025 | L10: =IF(Operations!L6>0,(1-Inputs!$C$11)^(Operations!L6-1),0) -> 0.990025 | ... BD10: =IF(Operations!BD6>0,(1-Inputs!$C$11)^(Operations!BD6-1),0) -> 0.88665351
B11: Seasonality | E11: 0.52 | F11: 0.48 | G11: 0.52 | H11: 0.48 | I11: 0.52 | J11: 0.48 | K11: 0.52 | L11: 0.48 | M11: 0.52 | N11: 0.48 | O11: 0.52 | P11: 0.48 | Q11: 0.52 | R11: 0.48 | S11: 0.52 | T11: 0.48 | U11: 0.52 | V11: 0.48 | W11: 0.52 | X11: 0.48 | Y11: 0.52 | Z11: 0.48 | AA11: 0.52 | AB11: 0.48 | AC11: 0.52 | AD11: 0.48 | AE11: 0.52 | AF11: 0.48 | AG11: 0.52 | AH11: 0.48 | AI11: 0.52 | AJ11: 0.48 | AK11: 0.52 | AL11: 0.48 | AM11: 0.52 | AN11: 0.48 | AO11: 0.52 | AP11: 0.48 | AQ11: 0.52 | AR11: 0.48 | AS11: 0.52 | AT11: 0.48 | AU11: 0.52 | AV11: 0.48 | AW11: 0.52 | AX11: 0.48 | AY11: 0.52 | AZ11: 0.48 | BA11: 0.52 | BB11: 0.48 | BC11: 0.52 | BD11: 0.48
B12: Production (MWh) | E12: =Inputs!$C$9*Inputs!$C$10*Inputs!$C$12*Operations!E10*Operations!E11 -> 0 | F12: =Inputs!$C$9*Inputs!$C$10*Inputs!$C$12*Operations!F10*Operations!F11 -> 0 | G12: =Inputs!$C$9*Inputs!$C$10*Inputs!$C$12*Operations!G10*Operations!G11/1000 -> 35905.22 | H12: =Inputs!$C$9*Inputs!$C$10*Inputs!$C$12*Operations!H10*Operations!H11/1000 -> 33143.28 | I12: =Inputs!$C$9*Inputs!$C$10*Inputs!$C$12*Operations!I10*Operations!I11/1000 -> 35725.694 | J12: =Inputs!$C$9*Inputs!$C$10*Inputs!$C$12*Operations!J10*Operations!J11/1000 -> 32977.564 | K12: =Inputs!$C$9*Inputs!$C$10*Inputs!$C$12*Operations!K10*Operations!K11/1000 -> 35547.065 | L12: =Inputs!$C$9*Inputs!$C$10*Inputs!$C$12*Operations!L10*Operations!L11/1000 -> 32812.676 | M12: =Inputs!$C$9*Inputs!$C$10*Inputs!$C$12*Operations!M10*Operations!M11/1000 -> 35369.33 | N12: =Inputs!$C$9*Inputs!$C$10*Inputs!$C$12*Operations!N10*Operations!N11/1000 -> 32648.612 | ... BD12: =Inputs!$C$9*Inputs!$C$10*Inputs!$C$12*Operations!BD10*Operations!BD11/1000 -> 29386.606
B14: REVENUE
B16: Price €/MWh | E16: =(Timing!E15*Inputs!$C$15)+(Inputs!$C$16*Timing!E16) -> 0 | F16: =(Timing!F15*Inputs!$C$15)+(Inputs!$C$16*Timing!F16) -> 0 | G16: =(Timing!G15*Inputs!$C$15)+(Inputs!$C$16*Timing!G16) -> 79 | H16: =(Timing!H15*Inputs!$C$15)+(Inputs!$C$16*Timing!H16) -> 79 | I16: =(Timing!I15*Inputs!$C$15)+(Inputs!$C$16*Timing!I16) -> 79 | J16: =(Timing!J15*Inputs!$C$15)+(Inputs!$C$16*Timing!J16) -> 79 | K16: =(Timing!K15*Inputs!$C$15)+(Inputs!$C$16*Timing!K16) -> 79 | L16: =(Timing!L15*Inputs!$C$15)+(Inputs!$C$16*Timing!L16) -> 79 | ... BD16: =(Timing!BD15*Inputs!$C$15)+(Inputs!$C$16*Timing!BD16) -> 55
B17: Revenue €m | E17: =E16*E12/1000000 -> 0 | F17: =F16*F12/1000000 -> 0 | G17: =G16*G12/1000000 -> 2.8365124 | H17: =H16*H12/1000000 -> 2.6183191 | I17: =I16*I12/1000000 -> 2.8223298 | J17: =J16*J12/1000000 -> 2.6052275 | K17: =K16*K12/1000000 -> 2.8082182 | L17: =L16*L12/1000000 -> 2.5922014 | ... BD17: =BD16*BD12/1000000 -> 1.6162633
B19: COSTS
B21: Opex €m | E21: =Inputs!$C$9*Inputs!$C$14*0.5*(1+Inputs!$C$27)^Operations!E6/1000000*Timing!E11 -> 0 | F21: =Inputs!$C$9*Inputs!$C$14*0.5*(1+Inputs!$C$27)^Operations!F6/1000000*Timing!F11 -> 0 | G21: =Inputs!$C$9*Inputs!$C$14*0.5*(1+Inputs!$C$27)^Operations!G6/1000000*Timing!G11 -> 0.408 | H21: =Inputs!$C$9*Inputs!$C$14*0.5*(1+Inputs!$C$27)^Operations!H6/1000000*Timing!H11 -> 0.408 | I21: =Inputs!$C$9*Inputs!$C$14*0.5*(1+Inputs!$C$27)^Operations!I6/1000000*Timing!I11 -> 0.41616 | J21: =Inputs!$C$9*Inputs!$C$14*0.5*(1+Inputs!$C$27)^Operations!J6/1000000*Timing!J11 -> 0.41616 | K21: =Inputs!$C$9*Inputs!$C$14*0.5*(1+Inputs!$C$27)^Operations!K6/1000000*Timing!K11 -> 0.4244832 | L21: =Inputs!$C$9*Inputs!$C$14*0.5*(1+Inputs!$C$27)^Operations!L6/1000000*Timing!L11 -> 0.4244832 | ... BD21: =Inputs!$C$9*Inputs!$C$14*0.5*(1+Inputs!$C$27)^Operations!BD6/1000000*Timing!BD11 -> 0.6562424
B23: EBITDA | E23: =E17-E21 -> 0 | F23: =F17-F21 -> 0 | G23: =G17-G21 -> 2.4285124 | H23: =H17-H21 -> 2.2103191 | I23: =I17-I21 -> 2.4061698 | J23: =J17-J21 -> 2.1890675 | K23: =K17-K21 -> 2.383735 | L23: =L17-L21 -> 2.1677182 | ... BD23: =BD17-BD21 -> 0.96002091
B25: TAX
B27: Depreciation | E27: =Construction!$C$36/Inputs!$C$24*Timing!E18*0.5 -> 0 | F27: =Construction!$C$36/Inputs!$C$24*Timing!F18*0.5 -> 0 | G27: =Construction!$C$36/Inputs!$C$24*Timing!G18*0.5 -> 1.0911139 | H27: =Construction!$C$36/Inputs!$C$24*Timing!H18*0.5 -> 1.0911139 | I27: =Construction!$C$36/Inputs!$C$24*Timing!I18*0.5 -> 1.0911139 | J27: =Construction!$C$36/Inputs!$C$24*Timing!J18*0.5 -> 1.0911139 | K27: =Construction!$C$36/Inputs!$C$24*Timing!K18*0.5 -> 1.0911139 | L27: =Construction!$C$36/Inputs!$C$24*Timing!L18*0.5 -> 1.0911139 | ... BD27: =Construction!$C$36/Inputs!$C$24*Timing!BD18*0.5 -> 0
B28: EBIT | E28: =E23-E27 -> 0 | F28: =F23-F27 -> 0 | G28: =G23-G27 -> 1.3373985 | H28: =H23-H27 -> 1.1192052 | I28: =I23-I27 -> 1.3150559 | J28: =J23-J27 -> 1.0979537 | K28: =K23-K27 -> 1.2926211 | L28: =L23-L27 -> 1.0766043 | ... BD28: =BD23-BD27 -> 0.96002091
B29: Interest | E29: =Debt!E30 -> 0 | F29: =Debt!F30 -> 0 | G29: =Debt!G30 -> 0.7303125 | H29: =Debt!H30 -> 0.71044635 | I29: =Debt!I30 -> 0.69345165 | J29: =Debt!J30 -> 0.6730524 | K29: =Debt!K30 -> 0.65549523 | L29: =Debt!L30 -> 0.63453827 | ... BD29: =Debt!BD30 -> 0
B30: Profit before tax | E30: =E28-E29 -> 0 | F30: =F28-F29 -> 0 | G30: =G28-G29 -> 0.60708601 | H30: =H28-H29 -> 0.4087589 | I30: =I28-I29 -> 0.62160429 | J30: =J28-J29 -> 0.42490125 | K30: =K28-K29 -> 0.63712587 | L30: =L28-L29 -> 0.44206604 | ... BD30: =BD28-BD29 -> 0.96002091
B31: Loss b/f | E31: =IF(E30<0,(D33+E30),0) -> 0 | F31: =IF(F30<0,(E33+F30),0) -> 0 | G31: =IF(G30<0,(F33+G30),0) -> 0 | H31: =IF(H30<0,(G33+H30),0) -> 0 | I31: =IF(I30<0,(H33+I30),0) -> 0 | J31: =IF(J30<0,(I33+J30),0) -> 0 | K31: =IF(K30<0,(J33+K30),0) -> 0 | L31: =IF(L30<0,(K33+L30),0) -> 0 | ... BD31: =IF(BD30<0,(BC33+BD30),0) -> 0
B32: Taxable profit | E32: =MAX(0,E30-E31) -> 0 | F32: =MAX(0,F30-F31) -> 0 | G32: =MAX(0,G30-G31) -> 0.60708601 | H32: =MAX(0,H30-H31) -> 0.4087589 | I32: =MAX(0,I30-I31) -> 0.62160429 | J32: =MAX(0,J30-J31) -> 0.42490125 | K32: =MAX(0,K30-K31) -> 0.63712587 | L32: =MAX(0,L30-L31) -> 0.44206604 | ... BD32: =MAX(0,BD30-BD31) -> 0.96002091
B33: Loss c/f | D33: 0 | E33: =MAX(0,E31-E30) -> 0 | F33: =MAX(0,F31-F30) -> 0 | G33: =MAX(0,G31-G30) -> 0 | H33: =MAX(0,H31-H30) -> 0 | I33: =MAX(0,I31-I30) -> 0 | J33: =MAX(0,J31-J30) -> 0 | K33: =MAX(0,K31-K30) -> 0 | L33: =MAX(0,L31-L30) -> 0 | ... BD33: =MAX(0,BD31-BD30) -> 0
B34: Tax | E34: =E32*Inputs!$C$23 -> 0 | F34: =F32*Inputs!$C$23 -> 0 | G34: =G32*Inputs!$C$23 -> 0.1517715 | H34: =H32*Inputs!$C$23 -> 0.10218973 | I34: =I32*Inputs!$C$23 -> 0.15540107 | J34: =J32*Inputs!$C$23 -> 0.10622531 | K34: =K32*Inputs!$C$23 -> 0.15928147 | L34: =L32*Inputs!$C$23 -> 0.11051651 | ... BD34: =BD32*Inputs!$C$23 -> 0.24000523
B35: PAT | E35: =E32-E34 -> 0 | F35: =F32-F34 -> 0 | G35: =G32-G34 -> 0.45531451 | H35: =H32-H34 -> 0.30656918 | I35: =I32-I34 -> 0.46620322 | J35: =J32-J34 -> 0.31867594 | K35: =K32-K34 -> 0.4778444 | L35: =L32-L34 -> 0.33154953 | ... BD35: =BD32-BD34 -> 0.72001568
B37: CFADS (EBITDA-Tax) | E37: =E23-E34 -> 0 | F37: =F23-F34 -> 0 | G37: =G23-G34 -> 2.2767409 | H37: =H23-H34 -> 2.1081294 | I37: =I23-I34 -> 2.2507687 | J37: =J23-J34 -> 2.0828422 | K37: =K23-K34 -> 2.2244535 | L37: =L23-L34 -> 2.0572017 | ... BD37: =BD23-BD34 -> 0.72001568

Sheet Debt
B2: DEBT — Sizing, sculpting, DSRA
B5: Period number | E5: 1 | F5: =E5+1 -> 2 | G5: =F5+1 -> 3 | H5: =G5+1 -> 4 | I5: =H5+1 -> 5 | J5: =I5+1 -> 6 | K5: =J5+1 -> 7 | L5: =K5+1 -> 8 | M5: =L5+1 -> 9 | ... BD5: =BC5+1 -> 52
B7: Semiannual rate | C7: =Inputs!C21/2 -> 0.02375
B9: DEBT SIZING
A11: A | B11: DSCR based capacity
B12: DSCR target | E12: =IF(Timing!E11=1,IF(Timing!E15=1,Inputs!$C$19,Inputs!$C$20),0) -> 0 | F12: =IF(Timing!F11=1,IF(Timing!F15=1,Inputs!$C$19,Inputs!$C$20),0) -> 0 | G12: =IF(Timing!G11=1,IF(Timing!G15=1,Inputs!$C$19,Inputs!$C$20),0) -> 1.55 | H12: =IF(Timing!H11=1,IF(Timing!H15=1,Inputs!$C$19,Inputs!$C$20),0) -> 1.55 | I12: =IF(Timing!I11=1,IF(Timing!I15=1,Inputs!$C$19,Inputs!$C$20),0) -> 1.55 | J12: =IF(Timing!J11=1,IF(Timing!J15=1,Inputs!$C$19,Inputs!$C$20),0) -> 1.55 | K12: =IF(Timing!K11=1,IF(Timing!K15=1,Inputs!$C$19,Inputs!$C$20),0) -> 1.55 | L12: =IF(Timing!L11=1,IF(Timing!L15=1,Inputs!$C$19,Inputs!$C$20),0) -> 1.55 | ... BD12: =IF(Timing!BD11=1,IF(Timing!BD15=1,Inputs!$C$19,Inputs!$C$20),0) -> 1.6
B13: Max debt service | E13: =IFERROR(Operations!E23/Debt!E12,0) -> 0 | F13: =IFERROR(Operations!F23/Debt!F12,0) -> 0 | G13: =IFERROR(Operations!G23/Debt!G12,0) -> 1.5667822 | H13: =IFERROR(Operations!H23/Debt!H12,0) -> 1.4260123 | I13: =IFERROR(Operations!I23/Debt!I12,0) -> 1.5523676 | J13: =IFERROR(Operations!J23/Debt!J12,0) -> 1.4123016 | K13: =IFERROR(Operations!K23/Debt!K12,0) -> 1.5378935 | L13: =IFERROR(Operations!L23/Debt!L12,0) -> 1.3985279 | ... BD13: =IFERROR(Operations!BD23/Debt!BD12,0) -> 0.60001307
B14: Discount factor | E14: =1/(1+$C$7)^Timing!E12 -> 1 | F14: =1/(1+$C$7)^Timing!F12 -> 1 | G14: =1/(1+$C$7)^Timing!G12 -> 0.97680098 | H14: =1/(1+$C$7)^Timing!H12 -> 0.95414015 | I14: =1/(1+$C$7)^Timing!I12 -> 0.93200503 | J14: =1/(1+$C$7)^Timing!J12 -> 0.91038342 | K14: =1/(1+$C$7)^Timing!K12 -> 0.88926342 | L14: =1/(1+$C$7)^Timing!L12 -> 0.86863337 | ... BD14: =1/(1+$C$7)^Timing!BD12 -> 0.30924612
B16: DSCR Capacity (€m) | C16: =SUMPRODUCT(Timing!E17:BD17,Debt!E13:BD13,Debt!E14:BD14) -> 33.451503
A18: B | B18: Gearing-based capacity
B20: Gearing capacity (€m) | C20: =Inputs!C18*Construction!C31 -> 30.75
B22: DEBT SIZE | C22: =MIN(C20,C16) -> 30.75
B23: Binding Constraint | C23: =IF(C20<C16,"Gearing-based","DSCR-based") -> Gearing-based
B26: REPAYMENT SCHEDULE
B28: Opening Balance | E28: 0 | F28: 0 | G28: =F34 -> 30.75 | H28: =G34 -> 29.91353 | I28: =H34 -> 29.197964 | J28: =I34 -> 28.339048 | K28: =J34 -> 27.599799 | L28: =K34 -> 26.717401 | M28: =L34 -> 25.953411 | N28: =M34 -> 25.046447 | ... BD28: =BC34 -> 0
B30: Interest | E30: 0 | F30: 0 | G30: =G28*$C$7 -> 0.7303125 | H30: =H28*$C$7 -> 0.71044635 | I30: =I28*$C$7 -> 0.69345165 | J30: =J28*$C$7 -> 0.6730524 | K30: =K28*$C$7 -> 0.65549523 | L30: =L28*$C$7 -> 0.63453827 | M30: =M28*$C$7 -> 0.61639352 | N30: =N28*$C$7 -> 0.59485312 | ... BD30: =BD28*$C$7 -> 0
B31: Target debt service | E31: 0 | F31: 0 | G31: =G13 -> 1.5667822 | H31: =H13 -> 1.4260123 | I31: =I13 -> 1.5523676 | J31: =J13 -> 1.4123016 | K31: =K13 -> 1.5378935 | L31: =L13 -> 1.3985279 | M31: =M13 -> 1.5233576 | N31: =N13 -> 1.3846887 | ... BD31: =BD13 -> 0.60001307
B32: Principal repayment | E32: 0 | F32: 0 | G32: =MIN(G28,MAX(0,G31-G30))*Timing!G17 -> 0.83646968 | H32: =MIN(H28,MAX(0,H31-H30))*Timing!H17 -> 0.71556599 | I32: =MIN(I28,MAX(0,I31-I30))*Timing!I17 -> 0.85891597 | J32: =MIN(J28,MAX(0,J31-J30))*Timing!J17 -> 0.73924923 | K32: =MIN(K28,MAX(0,K31-K30))*Timing!K17 -> 0.8823983 | L32: =MIN(L28,MAX(0,L31-L30))*Timing!L17 -> 0.76398959 | M32: =MIN(M28,MAX(0,M31-M30))*Timing!M17 -> 0.90696404 | N32: =MIN(N28,MAX(0,N31-N30))*Timing!N17 -> 0.7898356 | ... BD32: =MIN(BD28,MAX(0,BD31-BD30))*Timing!BD17 -> 0
B34: Closing Balance | E34: 0 | F34: =Debt!C22 -> 30.75 | G34: =G28-G32 -> 29.91353 | H34: =H28-H32 -> 29.197964 | I34: =I28-I32 -> 28.339048 | J34: =J28-J32 -> 27.599799 | K34: =K28-K32 -> 26.717401 | L34: =L28-L32 -> 25.953411 | M34: =M28-M32 -> 25.046447 | N34: =N28-N32 -> 24.256612 | ... BD34: =BD28-BD32 -> 0
B36: Actual debt service | E36: =E30+E32 -> 0 | F36: =F30+F32 -> 0 | G36: =G30+G32 -> 1.5667822 | H36: =H30+H32 -> 1.4260123 | I36: =I30+I32 -> 1.5523676 | J36: =J30+J32 -> 1.4123016 | K36: =K30+K32 -> 1.5378935 | L36: =L30+L32 -> 1.3985279 | ... BD36: =BD30+BD32 -> 0
B38: DSCR | E38: =IFERROR(Operations!E37/Debt!E36," ") | F38: =IFERROR(Operations!F37/Debt!F36," ") | G38: =IFERROR(Operations!G37/Debt!G36," ") -> 1.4531317 | H38: =IFERROR(Operations!H37/Debt!H36," ") -> 1.4783388 | I38: =IFERROR(Operations!I37/Debt!I36," ") -> 1.4498942 | J38: =IFERROR(Operations!J37/Debt!J36," ") -> 1.4747857 | K38: =IFERROR(Operations!K37/Debt!K36," ") -> 1.4464288 | L38: =IFERROR(Operations!L37/Debt!L36," ") -> 1.4709765 | ... BD38: =IFERROR(Operations!BD37/Debt!BD36," ")
B39: Min DSCR | C39: =MIN(E38:BD38) -> 1.3723361
B40: Avg DSCR | C40: =AVERAGE(E38:BD38) -> 1.6189127
B42: DSRA
B43: DSRA required | E43: =IFERROR(F36,0) -> 0 | F43: =IFERROR(G36,0) -> 1.5667822 | G43: =IFERROR(H36,0) -> 1.4260123 | H43: =IFERROR(I36,0) -> 1.5523676 | I43: =IFERROR(J36,0) -> 1.4123016 | J43: =IFERROR(K36,0) -> 1.5378935 | K43: =IFERROR(L36,0) -> 1.3985279 | L43: =IFERROR(M36,0) -> 1.5233576 | ... BD43: =IFERROR(BE36,0) -> 0
B44: DSRA opening | E44: =D46 -> 1.57 | F44: =E46 -> 0 | G44: =F46 -> 1.5667822 | H44: =G46 -> 1.4260123 | I44: =H46 -> 1.5523676 | J44: =I46 -> 1.4123016 | K44: =J46 -> 1.5378935 | L44: =K46 -> 1.3985279 | ... BD44: =BC46 -> 0
B45: DSRA movement | E45: =E43-E44 -> -1.57 | F45: =F43-F44 -> 1.5667822 | G45: =G43-G44 -> -0.14076985 | H45: =H43-H44 -> 0.12635529 | I45: =I43-I44 -> -0.140066 | J45: =J43-J44 -> 0.1255919 | K45: =K43-K44 -> -0.13936567 | L45: =L43-L44 -> 0.1248297 | ... BD45: =BD43-BD44 -> 0
B46: DSRA closing | D46: =Construction!C34 -> 1.57 | E46: =E43 -> 0 | F46: =F43 -> 1.5667822 | G46: =G43 -> 1.4260123 | H46: =H43 -> 1.5523676 | I46: =I43 -> 1.4123016 | J46: =J43 -> 1.5378935 | K46: =K43 -> 1.3985279 | L46: =L43 -> 1.5233576 | ... BD46: =BD43 -> 0

Sheet Returns
B2: RETURNS - Waterfall, IRR & LLCR
B5: Period number | E5: 1 | F5: =E5+1 -> 2 | G5: =F5+1 -> 3 | H5: =G5+1 -> 4 | I5: =H5+1 -> 5 | J5: =I5+1 -> 6 | K5: =J5+1 -> 7 | L5: =K5+1 -> 8 | M5: =L5+1 -> 9 | ... BD5: =BC5+1 -> 52
B7: CASH-FLOW WATERFALL
B9: CFADS | E9: =Operations!E37 -> 0 | F9: =Operations!F37 -> 0 | G9: =Operations!G37 -> 2.2767409 | H9: =Operations!H37 -> 2.1081294 | I9: =Operations!I37 -> 2.2507687 | J9: =Operations!J37 -> 2.0828422 | K9: =Operations!K37 -> 2.2244535 | L9: =Operations!L37 -> 2.0572017 | ... BD9: =Operations!BD37 -> 0.72001568
B10: Less: Senior interest | E10: =-Debt!E30 -> 0 | F10: =-Debt!F30 -> 0 | G10: =-Debt!G30 -> -0.7303125 | H10: =-Debt!H30 -> -0.71044635 | I10: =-Debt!I30 -> -0.69345165 | J10: =-Debt!J30 -> -0.6730524 | K10: =-Debt!K30 -> -0.65549523 | L10: =-Debt!L30 -> -0.63453827 | ... BD10: =-Debt!BD30 -> 0
B11: Less: Senior principal | E11: =-Debt!E32 -> 0 | F11: =-Debt!F32 -> 0 | G11: =-Debt!G32 -> -0.83646968 | H11: =-Debt!H32 -> -0.71556599 | I11: =-Debt!I32 -> -0.85891597 | J11: =-Debt!J32 -> -0.73924923 | K11: =-Debt!K32 -> -0.8823983 | L11: =-Debt!L32 -> -0.76398959 | ... BD11: =-Debt!BD32 -> 0
B13: Cash flow after debt service | E13: =E9+E10+E11 -> 0 | F13: =F9+F10+F11 -> 0 | G13: =G9+G10+G11 -> 0.7099587 | H13: =H9+H10+H11 -> 0.68211706 | I13: =I9+I10+I11 -> 0.69840112 | J13: =J9+J10+J11 -> 0.67054058 | K13: =K9+K10+K11 -> 0.68655997 | L13: =L9+L10+L11 -> 0.65867381 | ... BD13: =BD9+BD10+BD11 -> 0.72001568
B14: Less: DSRA movement | E14: =-Debt!E45 -> 1.57 | F14: =-Debt!F45 -> -1.5667822 | G14: =-Debt!G45 -> 0.14076985 | H14: =-Debt!H45 -> -0.12635529 | I14: =-Debt!I45 -> 0.140066 | J14: =-Debt!J45 -> -0.1255919 | K14: =-Debt!K45 -> 0.13936567 | L14: =-Debt!L45 -> -0.1248297 | ... BD14: =-Debt!BD45 -> 0
B15: Cash available for distribution | E15: =E13+E14 -> 1.57 | F15: =F13+F14 -> -1.5667822 | G15: =G13+G14 -> 0.85072854 | H15: =H13+H14 -> 0.55576177 | I15: =I13+I14 -> 0.83846712 | J15: =J13+J14 -> 0.54494868 | K15: =K13+K14 -> 0.82592564 | L15: =L13+L14 -> 0.53384412 | ... BD15: =BD13+BD14 -> 0.72001568
B16: Cumulative cash available for distribution | E16: =E15 -> 1.57 | F16: =E16+F15 -> 0.0032178194 | G16: =F16+G15 -> 0.85394636 | H16: =G16+H15 -> 1.4097081 | I16: =H16+I15 -> 2.2481752 | J16: =I16+J15 -> 2.7931239 | K16: =J16+K15 -> 3.6190496 | L16: =K16+L15 -> 4.1528937 | M16: =L16+M15 -> 4.965985 | ... BD16: =BC16+BD15 -> 43.411453
B18: Lock-up mechanism
B20: Lock up DSCR | C20: 1.1
B21: Lock up test | E21: =IF(Debt!E38>=Returns!$C$20,1,0) -> 1 | F21: =IF(Debt!F38>=Returns!$C$20,1,0) -> 1 | G21: =IF(Debt!G38>=Returns!$C$20,1,0) -> 1 | H21: =IF(Debt!H38>=Returns!$C$20,1,0) -> 1 | I21: =IF(Debt!I38>=Returns!$C$20,1,0) -> 1 | J21: =IF(Debt!J38>=Returns!$C$20,1,0) -> 1 | K21: =IF(Debt!K38>=Returns!$C$20,1,0) -> 1 | L21: =IF(Debt!L38>=Returns!$C$20,1,0) -> 1 | ... BD21: =IF(Debt!BD38>=Returns!$C$20,1,0) -> 1
B22: Cash distribution | E22: =E15*E21 -> 1.57 | F22: =F15*F21 -> -1.5667822 | G22: =G15*G21 -> 0.85072854 | H22: =H15*H21 -> 0.55576177 | I22: =I15*I21 -> 0.83846712 | J22: =J15*J21 -> 0.54494868 | K22: =K15*K21 -> 0.82592564 | L22: =L15*L21 -> 0.53384412 | ... BD22: =BD15*BD21 -> 0.72001568
B23: Cash trapped | E23: =E15-E22 -> 0 | F23: =F15-F22 -> 0 | G23: =G15-G22 -> 0 | H23: =H15-H22 -> 0 | I23: =I15-I22 -> 0 | J23: =J15-J22 -> 0 | K23: =K15-K22 -> 0 | L23: =L15-L22 -> 0 | ... BD23: =BD15-BD22 -> 0
B24: Cumulative cash trapped | E24: =E23 -> 0 | F24: =E24+F23 -> 0 | G24: =F24+G23 -> 0 | H24: =G24+H23 -> 0 | I24: =H24+I23 -> 0 | J24: =I24+J23 -> 0 | K24: =J24+K23 -> 0 | L24: =K24+L23 -> 0 | M24: =L24+M23 -> 0 | ... BD24: =BC24+BD23 -> 0
B26: LLCR
B27: NPV of CFADS over the debt term, discounted at borrowing rate, plus DSRA balance, divided by outstanding debt. | C27: =(SUMPRODUCT(Timing!E17:BD17,Operations!E37:BD37,Debt!E14:BD14)+Debt!E44)/Debt!G28 -> 1.6087553
B29: PROJECT CASH FLOW & RETURNS
B30: Tax charge (Project 100% equity funded) | E30: =(Operations!E32+Operations!E29)*Inputs!$C$23 -> 0 | F30: =(Operations!F32+Operations!F29)*Inputs!$C$23 -> 0 | G30: =(Operations!G32+Operations!G29)*Inputs!$C$23 -> 0.33434963 | H30: =(Operations!H32+Operations!H29)*Inputs!$C$23 -> 0.27980131 | I30: =(Operations!I32+Operations!I29)*Inputs!$C$23 -> 0.32876399 | J30: =(Operations!J32+Operations!J29)*Inputs!$C$23 -> 0.27448841 | K30: =(Operations!K32+Operations!K29)*Inputs!$C$23 -> 0.32315527 | L30: =(Operations!L32+Operations!L29)*Inputs!$C$23 -> 0.26915108 | ... BD30: =(Operations!BD32+Operations!BD29)*Inputs!$C$23 -> 0.24000523
B31: Project cash flow (Unlevered) | E31: =Operations!E23-E30-Construction!E8 -> -20.5 | F31: =Operations!F23-F30-Construction!F8 -> -20.5 | G31: =Operations!G23-G30-Construction!G8 -> 2.0941628 | H31: =Operations!H23-H30-Construction!H8 -> 1.9305178 | I31: =Operations!I23-I30-Construction!I8 -> 2.0774058 | J31: =Operations!J23-J30-Construction!J8 -> 1.9145791 | K31: =Operations!K23-K30-Construction!K8 -> 2.0605797 | L31: =Operations!L23-L30-Construction!L8 -> 1.8985671 | ... BD31: =Operations!BD23-BD30-Construction!BD8 -> 0.72001568
B33: Project IRR | C33: =IRR(E31:BD31) -> 0.035529655
B34: Project IRR annualised | C34: =(1+C33)^2-1 -> 0.072321667
B36: EQUITY IRR
B38: Equity cash flow | E38: =E22-Construction!E15 -> -6.1995549 | F38: =F22-Construction!F15 -> -6.6917822 | G38: =G22-Construction!G15 -> 0.85072854 | H38: =H22-Construction!H15 -> 0.55576177 | I38: =I22-Construction!I15 -> 0.83846712 | J38: =J22-Construction!J15 -> 0.54494868 | K38: =K22-Construction!K15 -> 0.82592564 | L38: =L22-Construction!L15 -> 0.53384412 | ... BD38: =BD22-Construction!BD15 -> 0.72001568
B40: Equity IRR | C40: =IRR(E38:BD38) -> 0.052313419
B41: Equity IRR annualised | C41: =(1+C40)^2-1 -> 0.10736353
B43: Equity MOIC | C43: =SUM(E22:BD22)/SUM(Construction!E15:F15) -> 3.36665
B45: Equity Payback - Cumulative cashflow | C45: ="Year "&ROUNDUP(COUNTIF(Returns!E45:BD45,"<0")/2,0) -> Year 11 | E45: =E38 -> -6.1995549 | F45: =E45+F38 -> -12.891337 | G45: =F45+G38 -> -12.040609 | H45: =G45+H38 -> -11.484847 | I45: =H45+I38 -> -10.64638 | J45: =I45+J38 -> -10.101431 | K45: =J45+K38 -> -9.2755053 | L45: =K45+L38 -> -8.7416612 | M45: =L45+M38 -> -7.9285699 | ... BD45: =BC45+BD38 -> 30.516898

Sheet Sensitivities
B2: SENSITIVITIES
B5: TABLE 1 · EQUITY IRR — PRODUCTION (P-CASE) × CONTRACT PRICE €/MWH
B7: Prod ↓ / Price → | C7: 70 | D7: 74 | E7: 79 | F7: 82 | G7: 85
B8: P90 | C8: 0.08366283 | D8: 0.087078339 | E8: 0.091259958 | F8: 0.093776849 | G8: 0.1003665
B9: P75 | C9: 0.087840234 | D9: 0.091331175 | E9: 0.097586217 | F9: 0.10427643 | G9: 0.11071392
B10: P50 | C10: 0.091851525 | D10: 0.095778142 | E10: 0.10736353 | F10: 0.11396969 | G10: 0.12039638
B11: P50+ | C11: 0.094185932 | D11: 0.10141678 | E11: 0.11291317 | F11: 0.11952556 | G11: 0.12596772
B14: TABLE 2 · EQUITY IRR — CAPEX (×) × PRODUCTION (P-CASE) [IDC CAVEAT]
B16: Capex ↓ / Prod → | C16: P90 | D16: P75 | E16: P50 | F16: P50+
B17: -10% | C17: 0.10236848 | D17: 0.11279268 | E17: 0.12259244 | F17: 0.12822596
B18: Base | C18: 0.091259958 | D18: 0.097586217 | E18: 0.10736353 | F18: 0.11291317
B19: +10% | C19: 0.086345956 | D19: 0.090517576 | E19: 0.094530248 | F19: 0.09914581
B20: +20% | C20: 0.081916355 | D20: 0.086023528 | E20: 0.089886986 | F20: 0.09213846
B23: TORNADO · EQUITY IRR SENSITIVITY (ONE-AT-A-TIME SWING FROM BASE)
B25: Driver | C25: Low | D25: High | E25: Swing
B26: Debt rate ±100bp | C26: 0.10382682 | D26: 0.11038123 | E26: 0.0065544032
B27: CfD price ±10% | C27: 0.092838788 | D27: 0.12438167 | E27: 0.03154288
B28: Production ±10% | C28: 0.091259958 | D28: 0.12518256 | E28: 0.033922605
B29: Capex ±15% | C29: 0.092139559 | D29: 0.13098173 | E29: 0.038842172
B44: Prepared by:
B45: Saud Shaikh
B46: saudshaikh044@gmail.com

Sheet Checks
B2: CHECKS
B5: Check description | C5: Test
B7: Master check | C7: =IF(AND(C9,C10,C11,C12,C13,C14,C15,C16,C17,C18,C19,C20,C21,C22,C23),"ALL CHECKS PASS","ONE OR MORE CHECKS FAILED") -> ALL CHECKS PASS
B9: Sources equals uses | C9: =ABS(Construction!C44-Construction!C36)<0.001 -> TRUE
B10: Debt drawdown equals debt sized | C10: =ABS((Construction!E14+Construction!F14)-Construction!C41)<0.001 -> TRUE
B11: Equity drawdown equals equity requirement | C11: =ABS((Construction!E15+Construction!F15)-Construction!C42)<0.001 -> TRUE
B12: Debt fully repaid at maturity | C12: =ABS(Debt!AP34) < 0.001 -> TRUE
B13: Debt stays positive | C13: =MIN(Debt!E34:BD34) > -0.001 -> TRUE
B14: DSRA releases to zero at maturity | C14: =ABS(Debt!AP46) < 0.001 -> TRUE
B15: Min. DSCR clears lock up covenant | C15: =Debt!C39 > 1.1 -> TRUE
B16: Construction flag sums to 2 | C16: =SUM(Timing!E10:BD10) = 2 -> TRUE
B17: Operations flag sums to 50 | C17: =SUM(Timing!E11:BD11) = 50 -> TRUE
B18: Contracted+merchant=Operations | C18: =(SUM(Timing!E15:BD15) + SUM(Timing!E16:BD16)) = SUM(Timing!E11:BD11) -> TRUE
B19: Debt repayment flag sums to tenor | C19: =SUM(Timing!E17:BD17) = Inputs!C7 -> TRUE
B20: Depreciation flas sums to dep. Period | C20: =SUM(Timing!E18:BD18) = Inputs!C25 -> TRUE
B21: Total depreciation equals depreciable base | C21: =ABS(SUM(Operations!E27:BD27) - Construction!C36) < 0.01 -> TRUE
B22: Production reconciles to capacity X yield | C22: =ABS(SUM(Operations!G12:H12) - (Inputs!C9*Inputs!C10*Inputs!C12/1000)) < 1 -> TRUE
B23: IDC check | C23: =AND(ABS(Construction!E22)<0.001, ABS(Construction!F22)<0.001) -> TRUE
